{"info_columns": ["adc_gain", "adc_res", "adc_zero", "baseline", "block_size", "comments", "date_reliability", "enddate", "fmt", "frequency", "init_vals", "length_ms", "pxx", "pxxxxxx", "record", "signals", "startdate", "subject_id", "subrecord", "type"], "signals_colums": ["%", "ABP", "ABPDias", "ABPMean", "ABPSys", "AOBP", "ART", "AVF", "AVL", "AVR", "CO", "CVP", "CVP_1/3", "CVP_2/3", "CVP_3/3", "HR", "I", "ICP", "II", "III", "LAP", "MCL", "MCL1", "NBP", "NBPDias", "NBPMean", "NBPSys", "P1", "PAP", "PAPDias", "PAPMean", "PAPSys", "PAWP", "PLETH", "PULSE", "PVC", "RAP", "RAP_1/3", "RAP_2/3", "RAP_3/3", "RESP", "ST", "ST_I", "ST_II", "UAP", "UVP", "V", "V1", "V2", "dSpO2"], "comorbidities_colums": ["congestive_heart_failure", "cardiac_arrhythmias", "valvular_disease", "pulmonary_circulation", "peripheral_vascular", "hypertension", "paralysis", "other_neurological", "chronic_pulmonary", "diabetes_uncomplicated", "diabetes_complicated", "hypothyroidism", "renal_failure", "liver_disease", "peptic_ulcer", "aids", "lymphoma", "metastatic_cancer", "solid_tumor", "rheumatoid_arthritis", "coagulopathy", "obesity", "weight_loss", "fluid_electrolyte", "blood_loss_anemia", "deficiency_anemias", "alcohol_abuse", "drug_abuse", "psychoses", "depression"], "plot_path": "figures/ABP_PPG/", "host": "localhost", "database": "mimic_wfdb", "user": "mimic", "password": "xxxx", "channels_selected_AND": ["PLETH"], "channels_selected_OR": ["ABP", "ART"], "channels_selected": ["PLETH", "ABP"], "drop_nan_limit": 1, "fs": 125, "q_signal": 2, "ventana": 15, "intervalo": 5, "signal_i": 10, "minutos_min": 15, "age_min": 18, "age_max": 90, "weight_min": 40, "weight_max": 180, "threshold_day": 2, "DBP_low": 50, "SBP_low": 80, "DBP_high": 120, "SBP_high": 200, "delta_DBP_valley": 7, "delta_SBP_peak": 30}